virtualshell/__init__.py
virtualshell/_core.cp39-win_amd64.pyd
virtualshell/_globals.py
virtualshell/_version.py
virtualshell/_vs_shm.dll
virtualshell/_vs_shm.lib
virtualshell/errors.py
virtualshell/generate_psobject.py
virtualshell/get-session.ps1
virtualshell/save-session.ps1
virtualshell/shell.py
virtualshell/zero_copy_bridge.ps1
virtualshell/zero_copy_bridge_shell.py
virtualshell-1.1.6.dist-info/METADATA
virtualshell-1.1.6.dist-info/WHEEL
virtualshell-1.1.6.dist-info/licenses/LICENSE
virtualshell-1.1.6.dist-info/RECORD
