Metadata-Version: 2.2
Name: virtualshell
Version: 1.1.6
Summary: High-performance PowerShell bridge (C++ pybind11 backend)
Keywords: powershell,automation,shell,cpp,pybind11
Author: Kim-Andre Myrvold
License:                                  Apache License
Classifier: Programming Language :: Python :: 3
Classifier: Programming Language :: Python :: 3 :: Only
Classifier: Programming Language :: C++
Classifier: Operating System :: Microsoft :: Windows
Classifier: Operating System :: POSIX :: Linux
Classifier: License :: OSI Approved :: Apache Software License
Project-URL: Homepage, https://github.com/Chamoswor/virtualshell
Project-URL: Issues, https://github.com/Chamoswor/virtualshell/issues
Requires-Python: >=3.8
